pytuneblade.py
pytuneblade-0.1.1.dist-info/METADATA
pytuneblade-0.1.1.dist-info/WHEEL
pytuneblade-0.1.1.dist-info/top_level.txt
pytuneblade-0.1.1.dist-info/RECORD
