Metadata-Version: 2.4
Name: pytuneblade
Version: 0.1.1
Summary: A Python interface to control TuneBlade remotely, built for Home Assistant integrations
Author-email: spycle <spycle@users.noreply.github.com>
License: MIT
Requires-Python: >=3.8
